README.md
setup.py
models/__init__.py
models/model.py
models/modulebank.py
models/tiramisu.py
models/layers/__init__.py
models/layers/blurpool.py
octopytorch.egg-info/PKG-INFO
octopytorch.egg-info/SOURCES.txt
octopytorch.egg-info/dependency_links.txt
octopytorch.egg-info/requires.txt
octopytorch.egg-info/top_level.txt
test/test_layers_blurpool.py
test/test_tiramisu.py