Metadata-Version: 2.1
Name: octopytorch
Version: 0.3
Summary: Segmentation Networks without a Backbone
Home-page: UNKNOWN
Author: Nicolas Pielawski
Author-email: nicolas@pielawski.fr
License: UNKNOWN
Platform: UNKNOWN
Classifier: Programming Language :: Python :: 3
Classifier: License :: OSI Approved :: MIT License
Classifier: Operating System :: OS Independent
